randomprojecttbd2/__init__.py
randomprojecttbd2/main_prog.py
randomprojecttbd2-0.0.4.dist-info/LICENSE
randomprojecttbd2-0.0.4.dist-info/METADATA
randomprojecttbd2-0.0.4.dist-info/WHEEL
randomprojecttbd2-0.0.4.dist-info/top_level.txt
randomprojecttbd2-0.0.4.dist-info/RECORD
