Metadata-Version: 2.1
Name: randomprojecttbd2
Version: 0.0.4
Summary: Learning to make a py package
Home-page: UNKNOWN
Author: Noone
Author-email: <mail@noone.com>
License: UNKNOWN
Keywords: python,terms-related-to-project
Platform: UNKNOWN
Classifier: Development Status :: 1 - Planning
Classifier: Intended Audience :: Developers
Classifier: Programming Language :: Python :: 3
Classifier: Operating System :: Unix
Classifier: Operating System :: MacOS :: MacOS X
Classifier: Operating System :: Microsoft :: Windows
Requires-Dist: numpy
Requires-Dist: scipy
Requires-Dist: tqdm
